modelshub/__init__.py
modelshub/models.py
modelshub-0.1.0.dist-info/METADATA
modelshub-0.1.0.dist-info/WHEEL
modelshub-0.1.0.dist-info/top_level.txt
modelshub-0.1.0.dist-info/RECORD
