Metadata-Version: 2.2
Name: modelshub
Version: 0.1.0
Summary: A unified interface for various LLM providers
Home-page: https://github.com/yourusername/modelshub
Author: Munakala Bharath
Author-email: bharathmunakala22@gmail.com
Classifier: Development Status :: 3 - Alpha
Classifier: Intended Audience :: Developers
Classifier: License :: OSI Approved :: MIT License
Classifier: Programming Language :: Python :: 3
Classifier: Programming Language :: Python :: 3.8
Classifier: Programming Language :: Python :: 3.9
Classifier: Programming Language :: Python :: 3.10
Classifier: Programming Language :: Python :: 3.11
Requires-Python: >=3.8
Requires-Dist: langchain>=0.1.0
Requires-Dist: langchain-google-genai>=0.0.5
Requires-Dist: langchain-openai>=0.0.2
Requires-Dist: langchain-groq>=0.0.1
Requires-Dist: langchain-anthropic>=0.0.1
Requires-Dist: python-dotenv>=1.0.0
Dynamic: author
Dynamic: author-email
Dynamic: classifier
Dynamic: description
Dynamic: description-content-type
Dynamic: home-page
Dynamic: requires-dist
Dynamic: requires-python
Dynamic: summary
